README.rst
setup.py
gcloudwrap/__init__.py
gcloudwrap/py.typed
gcloudwrap.egg-info/PKG-INFO
gcloudwrap.egg-info/SOURCES.txt
gcloudwrap.egg-info/dependency_links.txt
gcloudwrap.egg-info/requires.txt
gcloudwrap.egg-info/top_level.txt