Metadata-Version: 1.1
Name: gcloudwrap
Version: 1.0.5
Summary: wraps Google cloud client to facilitate deployment.
Home-page: https://github.com/Parquery/gcloudwrap
Author: Marko Ristin
Author-email: marko@parquery.com
License: UNKNOWN
Keywords: Google cloud gcloud deployment wrap
Platform: UNKNOWN
Classifier: Development Status :: 5 - Production/Stable
Classifier: Intended Audience :: Developers
Classifier: License :: OSI Approved :: MIT License
Classifier: Programming Language :: Python :: 3.5
